artek/__init__.py
artek/templates/__init__.py
artek/templates/apps.py
artek/templates/management/__init__.py
artek/templates/management/commands/__init__.py
artek/templates/management/commands/copy_templates.py
artek_templates-2.1.2.dist-info/METADATA
artek_templates-2.1.2.dist-info/WHEEL
artek_templates-2.1.2.dist-info/top_level.txt
artek_templates-2.1.2.dist-info/RECORD
